hypermodern_py/__init__.py
hypermodern_py/console.py
hypermodern_py/wikipedia.py
hypermodern_py-0.1.1.dist-info/entry_points.txt
hypermodern_py-0.1.1.dist-info/LICENSE
hypermodern_py-0.1.1.dist-info/WHEEL
hypermodern_py-0.1.1.dist-info/METADATA
hypermodern_py-0.1.1.dist-info/RECORD
